dib/__init__.py
dib/cli.py
dib/constants.py
dib/core.py
dibrowse-0.0.1.dist-info/LICENSE
dibrowse-0.0.1.dist-info/METADATA
dibrowse-0.0.1.dist-info/WHEEL
dibrowse-0.0.1.dist-info/entry_points.txt
dibrowse-0.0.1.dist-info/top_level.txt
dibrowse-0.0.1.dist-info/RECORD
