Metadata-Version: 2.1
Name: dibrowse
Version: 0.0.1
Summary: CLI tool 
Home-page: http://github.com/naestia/dib
Author: Viktor Berg
Author-email: viktor.david.berg@gmail.com
Maintainer: Viktor Berg
Maintainer-email: viktor.david.berg@gmail.com
Classifier: Development Status :: 2 - Pre-Alpha
Classifier: Intended Audience :: Developers
Classifier: Operating System :: Unix
Classifier: License :: OSI Approved :: Apache Software License
Classifier: Environment :: Console
Classifier: Programming Language :: Python
Classifier: Programming Language :: Python :: 3
Classifier: Programming Language :: Python :: 3.8
Classifier: Programming Language :: Python :: 3.9
Classifier: Programming Language :: Python :: 3.10
Classifier: Programming Language :: Python :: 3.11
Classifier: Natural Language :: English
Requires-Python: >=3.8
License-File: LICENSE
Requires-Dist: docopt (>=0.6.2)
Requires-Dist: packaging (>=21.3)
Requires-Dist: pyperclip (>=1.8.2)
Provides-Extra: dev
Requires-Dist: pylint ; extra == 'dev'
Provides-Extra: test
Requires-Dist: pytest ; extra == 'test'
Requires-Dist: pytest-mock ; extra == 'test'
Requires-Dist: flake8 ; extra == 'test'
